autogoal_streamlit/__init__.py
autogoal_streamlit/cli.py
autogoal_streamlit/demo.py
autogoal_streamlit-0.8.4.dist-info/WHEEL
autogoal_streamlit-0.8.4.dist-info/METADATA
autogoal_streamlit-0.8.4.dist-info/RECORD
